src/Parameter.v
// =========================================================================
// Practical 4: StarCore-1 — Single-Cycle Processor in Verilog
// =========================================================================
//
// GROUP NUMBER:16
//
// MEMBERS:
//   - Member 1 Zameer Mahomed, MHMZAM005
//   - Member 2 Mahir Khan, KHNMAH014

// File        : Parameter.v
// Description : Shared compile-time parameters used across all modules.
//               Include this file at the top of every .v file:
//                   `include "../src/Parameter.v"
// =============================================================================

`ifndef PARAMETER_H_
`define PARAMETER_H_

// ---------------------------------------------------------------------------
// Memory dimensions
// ---------------------------------------------------------------------------
`define COL     16          // Data/instruction word width (bits)
`define ROW_I   16          // Instruction memory depth (words, 16 x 16-bit)
`define ROW_D    8          // Data memory depth (words,  8 x 16-bit)

// ---------------------------------------------------------------------------
// Simulation control
// Increase SIM_TIME if your test program needs more clock cycles to complete.
// At 10 ns per clock (100 MHz) each #10 is one half-period; 320 ns = 16 cycles.
// ---------------------------------------------------------------------------
//`define SIM_TIME  #640      // Total simulation time for integration testbench
//`define SIM_TIME  #115      // Total simulation time for one run
//`define SIM_TIME  #30   // test 1: stop after ADD R2. 
//`define SIM_TIME  #40   // test 1: stop after ADD R2. 
//`define SIM_TIME  #55      // Test SUB
//`define SIM_TIME  #125      // Total simulation time + jump
`define SIM_TIME  #160       // One full program pass: captures state just after JMP commits (PC=0)

// ---------------------------------------------------------------------------
// Output file for data-memory dump (used in DataMemory.v $fmonitor)
// ---------------------------------------------------------------------------
`define DMEM_LOG  "./waves/dmem_log.txt"

`endif  // PARAMETER_H_

src/Encoder.v
// =========================================================================
// Project ErrCo: ErrCo StarCore-1 Co-Proccessor Encoding Module
// =========================================================================
//
// Project Group 10
//
// MEMBERS:
//   - Member 1 Zameer Mahomed, MHMZAM005
//   - Member 2 Mahir Khan, KHNMAH014

// File        : Encoder.v
// Description : SEC-DED Hamming(22,16) 6-bit Parity Generator
//
// =============================================================================

`timescale 1ns / 1ps
//`include "../src/Parameter.v"

//module definition
module Encoder (
    input [15:0] data_in, // 16-bit of data to perform Hamming XOR on
    output [5:0] parity //calculated 6-bit parity
);
    //declare 6 single-bit wires to represent 6-parity bits
    wire p0;
    wire p1;
    wire p2;
    wire p3;
    wire p4;
    wire p5;

    //-----------XOR------------
    //Follow Hamming Matrix
    //all powers of 2 are parity bits and rest are data
    //This means d0,d1,d3 & d15 are removed:giving mapping for XOR:
    //pos 0 - p0: 0,1,3,4,6,8,10,11,13.15
    //pos 1 - p1: 0,2,3,5,6,9,10,12,13
    //pos 2 - p2: 1,2,3,7,8,9,10,14,15
    //pos 4 - p3: 4,5,6,7,8,9,10
    //pos 8 - p4: 11,12,13,14,15
    //pos 16- p5: 1-15,p1-p4

    //XOR TREE

    assign p0 = data_in[0] ^ data_in[1] ^ data_in[3] ^ data_in[4] ^ data_in[6] ^ data_in[8] ^ data_in[10] ^ data_in[11] ^ data_in[13] ^ data_in[15];

    assign p1 = data_in[0]^data_in[2]^data_in[3]^data_in[5]^data_in[6]^data_in[9]^data_in[10]^data_in[12]^data_in[13];

    assign p2 = data_in[1]^data_in[2]^data_in[3]^data_in[7]^data_in[8]^data_in[9]^data_in[10]^data_in[14]^data_in[15];

    assign p3 = data_in[4]^data_in[5]^data_in[6]^data_in[7]^data_in[8]^data_in[9]^data_in[10];

    assign p4 = data_in[11]^data_in[12]^data_in[13]^data_in[14]^data_in[15];

    assign p5 = (^data_in) ^ p0 ^ p1 ^ p2 ^ p3 ^ p4;

    //create 6-bit parity from p0-p5
    assign parity = {p5,p4, p3, p2, p1, p0};

endmodule

src/Decoder.v
// =========================================================================
// Project ErrCo: ErrCo StarCore-1 Co-Proccessor Decoding Module Testbench
// =========================================================================
//
// Project Group 10
//
// MEMBERS:
//   - Member 1 Zameer Mahomed, MHMZAM005
//   - Member 2 Mahir Khan, KHNMAH014

// File        : Decoder.v
// Description : SEC-DED Hamming(22,16) 6-bit Error Syndrome Calculator and Single Bit Corrector
//
// =============================================================================

`timescale 1ns / 1ps
//`include "../src/Parameter.v"

//module definition
module Decoder (
    input [15:0] data_in, // 16-bit of data to perform Hamming XOR on
    input [5:0] parity, //corresponding 6-bit parity from the parity store

    //-------Outputs---------
    output reg [15:0] Error_Corr_Result, //corrected output result
    output SE_flag, // Single error detected (used for debugging in GTKWAVE)
    output DE_flag, // Unsued output flag to indicate double error has occured
    output parity_bit_error // ADDED: SE detected AND syndrome points to a parity bit (1,2,4,8,16) - data is clean, parity is corrupted
);

// ------Decoder Wires ---------
    //Parity Recalulation
    //declare 6 single-bit wires to represent 6-parity bits for decoder to calculate
    wire p0;
    wire p1;
    wire p2;
    wire p3;
    wire p4;
    wire p5;
    wire [5:0]  decoder_parity;     //parity of data to be checked

    //Error Syndrome wires
    wire [4:0]  error_syndrome;     // wire stores calculated 5-bit single error Syndrome
    wire        p5_error_check;     //6th bit parity double_error_check checks if double error has occured

    //TODO, should vlaues be defeualetd to zero?

// --------------Same Parity logic from Encoder Module --------------------
    //-----------XOR------------
    //Follow Hamming Matrix
    //all powers of 2 are parity bits and rest are data
    //This means d0,d1,d3 & d15 are removed:giving mapping for XOR:
    //pos 0 - p0: 0,1,3,4,6,8,10,11,13.15
    //pos 1 - p1: 0,2,3,5,6,9,10,12,13
    //pos 2 - p2: 1,2,3,7,8,9,10,14,15
    //pos 4 - p3: 4,5,6,7,8,9,10
    //pos 8 - p4: 11,12,13,14,15
    //pos 16- p5: 1-15,p1-p4

    //XOR TREE

    assign p0 = data_in[0] ^ data_in[1] ^ data_in[3] ^ data_in[4] ^ data_in[6] ^ data_in[8] ^ data_in[10] ^ data_in[11] ^ data_in[13] ^ data_in[15];

    assign p1 = data_in[0]^data_in[2]^data_in[3]^data_in[5]^data_in[6]^data_in[9]^data_in[10]^data_in[12]^data_in[13];

    assign p2 = data_in[1]^data_in[2]^data_in[3]^data_in[7]^data_in[8]^data_in[9]^data_in[10]^data_in[14]^data_in[15];

    assign p3 = data_in[4]^data_in[5]^data_in[6]^data_in[7]^data_in[8]^data_in[9]^data_in[10];

    assign p4 = data_in[11]^data_in[12]^data_in[13]^data_in[14]^data_in[15];

    // FIXED: p5 (overall SEC-DED parity) recomputed from STORED parity bits, not
    // freshly-recomputed ones. Otherwise a SEU in a stored parity bit is invisible
    // to p5_error_check and gets misreported as a double error.
    assign p5 = (^data_in) ^ parity[0] ^ parity[1] ^ parity[2] ^ parity[3] ^ parity[4];

    //create 6-bit parity from p0-p5
    assign decoder_parity = {p5,p4, p3, p2, p1, p0};

    //-------- Decoder: Syndrome calculation ----------
    assign error_syndrome = decoder_parity[4:0] ^ parity[4:0];  //XOR calc with expected parity
    assign p5_error_check = decoder_parity[5] ^ parity[5];      //XOR extra calc bit with expected extra parity

    //-------- Decoder: Error detection ----------
    // if error_syndrome !=0, then theres definitely a single or more bit error
    // if p5_error_check == 0, then even number of XOR flips, so indicates double or quadruple etc, error has occured
    // if both error_syndrome !=0 and p5_error_check is 1, then there is definitely a single bit error
    //NOTE: technically this flag could pass for 3 or more bit errors - but with 6-parity, not checking for them here and assuming 3 or more bit is unlikely

    // FIXED: SEC-DED decode table -> a single error exists whenever the overall
    // parity check fails. Also covers the case where p5 itself is the flipped bit
    // (error_syndrome==0, p5_error_check==1): data is clean, correction case block
    // falls through to default and leaves it untouched.
    assign SE_flag = p5_error_check; //SE flag 1 means Single bit error

    // if p5_error_check is now 0, there is definitely a double error

    //assign DE_flag = (error_syndrome != 5'b0) && (p5_error_check == 1'b0); //DE flag = 1 means double bit error.
    assign DE_flag = (error_syndrome != 5'b0) && (p5_error_check == 1'b0); //DE flag = 1 means double bit error.

    // -------- Decoder: Parity-Bit Error Detection ----------
    // ADDED: parity_bit_error asserts when SE is high but the syndrome lands at a parity-bit position
    // (1, 2, 4, 8, or 16). In this case the data bits are clean - it is the stored parity that was corrupted.
    // Used by SCRUB (1010 sub-op 01) to know whether to refresh ParityStore.
    assign parity_bit_error = SE_flag && (
        (error_syndrome == 5'd1)  ||
        (error_syndrome == 5'd2)  ||
        (error_syndrome == 5'd4)  ||
        (error_syndrome == 5'd8)  ||
        (error_syndrome == 5'd16)
    );

    //-------- Decoder: Error Correction ----------

    // The codeword with parity bits is 22-bit as parity bits are powers of 2
    //each power of 2 index is removed, so indices of syndrome need to reflect that

    // =============================================================================
    // VISUAL SYNDROME TO DATA BIT MAPING TABLE
    // -----------------------------------------------------------------------------
    // Syndrome (Dec) | Codeword Pos | Targeted Bit | Note
    // -----------------------------------------------------------------------------
    //      3         |    Pos 3     |  data_in[0]  | First Data Bit
    //      5         |    Pos 5     |  data_in[1]  |
    //      6         |    Pos 6     |  data_in[2]  |
    //      7         |    Pos 7     |  data_in[3]  |
    //      9         |    Pos 9     |  data_in[4]  | After  Parity P3 (Pos 8)
    //      10        |    Pos 10    |  data_in[5]  |
    //      11        |    Pos 11    |  data_in[6]  |
    //      12        |    Pos 12    |  data_in[7]  |
    //      13        |    Pos 13    |  data_in[8]  |
    //      14        |    Pos 14    |  data_in[9]  |
    //      15        |    Pos 15    |  data_in[10] |
    //      17        |    Pos 17    |  data_in[11] |  After Parity P4 (Pos 16)
    //      18        |    Pos 18    |  data_in[12] |
    //      19        |    Pos 19    |  data_in[13] |
    //      20        |    Pos 20    |  data_in[14] |
    //      21        |    Pos 21    |  data_in[15] | Last Data Bit
    // =============================================================================


    always @(*) begin
        //default case leave data alone & set output as the input data
        Error_Corr_Result = data_in;

        if (SE_flag) begin //only start if single bit error
            case(error_syndrome) // based on what postion syndrome has identified
                // bit flip corresponding bit
                5'd3 : Error_Corr_Result[0] = ~data_in[0];
                5'd5 : Error_Corr_Result[1] = ~data_in[1];
                5'd6 : Error_Corr_Result[2] = ~data_in[2];
                5'd7 : Error_Corr_Result[3] = ~data_in[3];
                5'd9 : Error_Corr_Result[4] = ~data_in[4];
                5'd10: Error_Corr_Result[5] = ~data_in[5];
                5'd11: Error_Corr_Result[6] = ~data_in[6];
                5'd12: Error_Corr_Result[7] = ~data_in[7];
                5'd13: Error_Corr_Result[8] = ~data_in[8];
                5'd14: Error_Corr_Result[9] = ~data_in[9];
                5'd15: Error_Corr_Result[10] = ~data_in[10];
                5'd17: Error_Corr_Result[11] = ~data_in[11];
                5'd18: Error_Corr_Result[12] = ~data_in[12];
                5'd19: Error_Corr_Result[13] = ~data_in[13];
                5'd20: Error_Corr_Result[14] = ~data_in[14];
                5'd21: Error_Corr_Result[15] = ~data_in[15];
                default: Error_Corr_Result = data_in; //default case
            endcase
        end
    end

endmodule

tb/Decoder_tb.v
`timescale 1ns / 1ps

module Decoder_tb;

    reg     [15:0] data_in;
    reg     [5:0] parity;

    wire    [15:0] Error_Corr_Result;
    wire    SE_flag;
    wire    DE_flag;
    wire    parity_bit_error;

    Decoder uut (
        .data_in(data_in),
        .parity(parity),
        .Error_Corr_Result(Error_Corr_Result),
        .SE_flag(SE_flag),
        .DE_flag(DE_flag),
        .parity_bit_error(parity_bit_error)
    );

    // Encoder instance so the tb can compute correct parity for any data word
    reg  [15:0] enc_data;
    wire [5:0]  enc_parity;
    Encoder tb_enc (
        .data_in (enc_data),
        .parity  (enc_parity)
    );

    initial begin
        $dumpfile("../waves/Decoder_tb.vcd");
        $dumpvars(0, Decoder_tb);
    end

    integer fail_count;
    integer test_id;
    integer k;
    integer fb;

    initial begin
        fail_count = 0;
        test_id    = 1;
    end

    task check_result;
        input [15:0] got;
        input [15:0] expected;
        input got_SE;
        input expected_SE;
        input got_DE;
        input expected_DE;
        input got_PE;
        input expected_PE;
        input [63:0] id;
        begin
            if (got == expected && got_SE == expected_SE && got_DE==expected_DE && got_PE == expected_PE) begin
                $display("PASS [T%0d]: result = %0b (0x%h), expected = %0b (0x%h) | SE=%b DE=%b PE=%b", id, got, got, expected, expected, got_SE, got_DE, got_PE);
            end else begin
                $display("FAIL [T%0d]: result = %0b (0x%h), expected = %0b (0x%h)",
                         id, got, got, expected, expected);
                $display("           SE got=%b exp=%b | DE got=%b exp=%b | PE got=%b exp=%b",
                         got_SE, expected_SE, got_DE, expected_DE, got_PE, expected_PE);
                fail_count = fail_count + 1;
            end
        end
    endtask

initial begin
        $display("=== Decoder Testbench (extended) ===");

        $display("Test1: Correction of Single Bit Error");
        data_in = 16'h0001; parity = 6'b000000; #10;
        check_result(Error_Corr_Result, 16'h0000, SE_flag, 1'b1, DE_flag, 1'b0, parity_bit_error, 1'b0, test_id);
        test_id = test_id + 1;

        $display("Test2: Correction of Single Bit Error");
        data_in = 16'h0000; parity = 6'b100011; #10;
        check_result(Error_Corr_Result, 16'h0001, SE_flag, 1'b1, DE_flag, 1'b0, parity_bit_error, 1'b0, test_id);
        test_id = test_id + 1;

        $display("Test 3: Correction of Single Bit Error");
        data_in = 16'hFFFE; parity = 6'b011110; #10;
        check_result(Error_Corr_Result, 16'hFFFF, SE_flag, 1'b1, DE_flag, 1'b0, parity_bit_error, 1'b0, test_id);
        test_id = test_id + 1;

        $display("Test 4: Correction of Single Bit Error");
        data_in = 16'h0810; parity = 6'b110001; #10;
        check_result(Error_Corr_Result, 16'h0800, SE_flag, 1'b1, DE_flag, 1'b0, parity_bit_error, 1'b0, test_id);
        test_id = test_id + 1;

        // T5: parity 100011 is the valid parity for 0x0001; data 0x0101 is ONE
        // data bit (bit 8) away from that codeword -> single error, corrects to 0x0001.
        $display("Test 5: Single Bit Error (data bit 8) -> corrects to 0x0001");
        data_in = 16'h0101; parity = 6'b100011; #10;
        check_result(Error_Corr_Result, 16'h0001, SE_flag, 1'b1, DE_flag, 1'b0, parity_bit_error, 1'b0, test_id);
        test_id = test_id + 1;

        // T6: parity 100011 is valid for 0x0001; data 0x0111 is TWO data bits
        // (bits 4 and 8) away -> genuine double error, DE=1, data left unchanged.
        $display("Test 6: Double Error (data bits 4 and 8) -> DE flagged");
        data_in = 16'h0111; parity = 6'b100011; #10;
        check_result(Error_Corr_Result, 16'h0111, SE_flag, 1'b0, DE_flag, 1'b1, parity_bit_error, 1'b0, test_id);
        test_id = test_id + 1;

        // Tests 7..94 exhaustive single-bit-flip sweep
        $display("");
        $display("--- Tests 7-94: exhaustive single-bit-flip sweep ---");
        for (k = 0; k < 4; k = k + 1) begin
            case (k)
                0: enc_data = 16'h0000;
                1: enc_data = 16'hFFFF;
                2: enc_data = 16'hA5A5;
                3: enc_data = 16'h1234;
            endcase
            #5;
            for (fb = 0; fb < 16; fb = fb + 1) begin
                data_in = enc_data ^ (16'b1 << fb);
                parity  = enc_parity;
                #10;
                check_result(Error_Corr_Result, enc_data,
                             SE_flag, 1'b1, DE_flag, 1'b0,
                             parity_bit_error, 1'b0, test_id);
                test_id = test_id + 1;
            end
            for (fb = 0; fb < 6; fb = fb + 1) begin
                data_in = enc_data;
                parity  = enc_parity ^ (6'b1 << fb);
                #10;
                check_result(Error_Corr_Result, enc_data,
                             SE_flag, 1'b1, DE_flag, 1'b0,
                             parity_bit_error, (fb < 5) ? 1'b1 : 1'b0, test_id);
                test_id = test_id + 1;
            end
        end

        $display("");
        $display("--- Test 95: clean codeword (no error) ---");
        enc_data = 16'hA5A5; #5;
        data_in = enc_data;
        parity  = enc_parity;
        #10;
        check_result(Error_Corr_Result, enc_data,
                     SE_flag, 1'b0, DE_flag, 1'b0,
                     parity_bit_error, 1'b0, test_id);
        test_id = test_id + 1;

        $display("");
        if (fail_count == 0)
            $display("=== ALL %0d TESTS PASSED ===", test_id - 1);
        else
            $display("=== %0d / %0d TESTS FAILED ===", fail_count, test_id - 1);

        $finish;
    end

endmodule

waves/Decoder_tb.vcd
$date
	Thu May 14 22:11:35 2026
$end
$version
	Icarus Verilog
$end
$timescale
	1ps
$end
$scope module Decoder_tb $end
$var wire 1 ! parity_bit_error $end
$var wire 6 " enc_parity [5:0] $end
$var wire 1 # SE_flag $end
$var wire 16 $ Error_Corr_Result [15:0] $end
$var wire 1 % DE_flag $end
$var reg 16 & data_in [15:0] $end
$var reg 16 ' enc_data [15:0] $end
$var reg 6 ( parity [5:0] $end
$var integer 32 ) fail_count [31:0] $end
$var integer 32 * fb [31:0] $end
$var integer 32 + k [31:0] $end
$var integer 32 , test_id [31:0] $end
$scope module tb_enc $end
$var wire 16 - data_in [15:0] $end
$var wire 1 . p0 $end
$var wire 1 / p1 $end
$var wire 1 0 p2 $end
$var wire 1 1 p3 $end
$var wire 1 2 p4 $end
$var wire 1 3 p5 $end
$var wire 6 4 parity [5:0] $end
$upscope $end
$scope module uut $end
$var wire 1 % DE_flag $end
$var wire 1 # SE_flag $end
$var wire 16 5 data_in [15:0] $end
$var wire 5 6 error_syndrome [4:0] $end
$var wire 1 7 p0 $end
$var wire 1 8 p1 $end
$var wire 1 9 p2 $end
$var wire 1 : p3 $end
$var wire 1 ; p4 $end
$var wire 1 < p5 $end
$var wire 1 = p5_error_check $end
$var wire 6 > parity [5:0] $end
$var wire 1 ! parity_bit_error $end
$var wire 6 ? decoder_parity [5:0] $end
$var reg 16 @ Error_Corr_Result [15:0] $end
$upscope $end
$scope task check_result $end
$var reg 16 A expected [15:0] $end
$var reg 1 B expected_DE $end
$var reg 1 C expected_PE $end
$var reg 1 D expected_SE $end
$var reg 16 E got [15:0] $end
$var reg 1 F got_DE $end
$var reg 1 G got_PE $end
$var reg 1 H got_SE $end
$var reg 64 I id [63:0] $end
$upscope $end
$upscope $end
$enddefinitions $end
$comment Show the parameter values. $end
$dumpall
$end
#0
$dumpvars
bx I
xH
xG
xF
bx E
xD
xC
xB
bx A
b0 @
b100011 ?
b0 >
1=
1<
0;
0:
09
18
17
b11 6
b1 5
bx 4
x3
x2
x1
x0
x/
x.
bx -
b1 ,
bx +
bx *
b0 )
b0 (
bx '
b1 &
0%
b0 $
1#
bx "
0!
$end
#10000
0!
07
08
b0 ?
0<
b11 6
1#
1=
b1 $
b1 @
b100011 (
b100011 >
b0 &
b0 5
b10 ,
b1 I
0C
0G
0B
0F
1D
1H
b0 A
b0 E
#20000
0!
0%
1<
b11 6
1#
1=
17
08
19
1:
b111101 ?
1;
b1111111111111111 $
b1111111111111111 @
b11110 (
b11110 >
b1111111111111110 &
b1111111111111110 5
b11 ,
b10 I
b1 A
b1 E
#30000
0!
0%
0<
b1001 6
1#
1=
07
08
09
1:
b11000 ?
1;
b100000000000 $
b100000000000 @
b110001 (
b110001 >
b100000010000 &
b100000010000 5
b100 ,
b11 I
b1111111111111111 A
b1111111111111111 E
#40000
0!
18
0%
19
0;
1#
1=
07
1:
b1110 ?
0<
b1101 6
b1 $
b1 @
b100011 (
b100011 >
b100000001 &
b100000001 5
b101 ,
b100 I
b100000000000 A
b100000000000 E
#50000
b100 6
1%
17
0:
0#
0=
b100111 ?
1<
b100010001 $
b100010001 @
b100010001 &
b100010001 5
b110 ,
b101 I
b1 A
b1 E
#60000
03
0.
0/
00
01
b0 "
b0 4
02
b0 '
b0 -
b0 +
b111 ,
b110 I
1B
1F
0D
0H
b100010001 A
b100010001 E
#65000
17
09
1<
0%
b100011 ?
0:
0!
b11 6
1#
1=
b0 $
b0 @
b0 (
b0 >
b1 &
b1 5
b0 *
#75000
b101 6
08
b100101 ?
19
b0 $
b0 @
b10 &
b10 5
b1 *
b1000 ,
b111 I
0B
0F
1D
1H
b0 A
b0 E
#85000
b110 6
07
b100110 ?
18
b0 $
b0 @
b100 &
b100 5
b10 *
b1001 ,
b1000 I
#95000
b111 6
17
18
b100111 ?
19
b0 $
b0 @
b1000 &
b1000 5
b11 *
b1010 ,
b1001 I
#105000
0!
b1001 6
17
08
09
b101001 ?
1:
b0 $
b0 @
b10000 &
b10000 5
b100 *
b1011 ,
b1010 I
#115000
b1010 6
07
b101010 ?
18
b0 $
b0 @
b100000 &
b100000 5
b101 *
b1100 ,
b1011 I
#125000
b1011 6
17
18
b101011 ?
1:
b0 $
b0 @
b1000000 &
b1000000 5
b110 *
b1101 ,
b1100 I
#135000
07
19
b1100 6
08
b101100 ?
1:
b0 $
b0 @
b10000000 &
b10000000 5
b111 *
b1110 ,
b1101 I
#145000
0!
17
19
b1101 6
b101101 ?
1:
b0 $
b0 @
b100000000 &
b100000000 5
b1000 *
b1111 ,
b1110 I
#155000
07
18
19
b1110 6
b101110 ?
1:
b0 $
b0 @
b1000000000 &
b1000000000 5
b1001 *
b10000 ,
b1111 I
#165000
0!
17
18
19
b1111 6
b101111 ?
1:
b0 $
b0 @
b10000000000 &
b10000000000 5
b1010 *
b10001 ,
b10000 I
#175000
0!
1;
17
08
09
b10001 6
b110001 ?
0:
b0 $
b0 @
b100000000000 &
b100000000000 5
b1011 *
b10010 ,
b10001 I
#185000
b10010 6
07
b110010 ?
18
b0 $
b0 @
b1000000000000 &
b1000000000000 5
b1100 *
b10011 ,
b10010 I
#195000
0!
b10011 6
1;
17
b110011 ?
18
b0 $
b0 @
b10000000000000 &
b10000000000000 5
b1101 *
b10100 ,
b10011 I
#205000
b10100 6
07
19
1;
b110100 ?
08
b0 $
b0 @
b100000000000000 &
b100000000000000 5
b1110 *
b10101 ,
b10100 I
#215000
0!
b10101 6
17
19
b110101 ?
1;
b0 $
b0 @
b1000000000000000 &
b1000000000000000 5
b1111 *
b10110 ,
b10101 I
#225000
1!
0%
1#
1=
1<
b1 6
07
09
b100000 ?
0;
b0 $
b0 @
b1 (
b1 >
b0 &
b0 5
b0 *
b10111 ,
b10110 I
#235000
0%
1!
1#
1=
b100000 ?
1<
b10 6
b10 (
b10 >
b1 *
b11000 ,
b10111 I
1C
1G
#245000
0%
1!
1#
1=
b100000 ?
1<
b100 6
b100 (
b100 >
b10 *
b11001 ,
b11000 I
#255000
0%
1!
1#
1=
b100000 ?
1<
b1000 6
b1000 (
b1000 >
b11 *
b11010 ,
b11001 I
#265000
0%
1!
1#
1=
b100000 ?
1<
b10000 6
b10000 (
b10000 >
b100 *
b11011 ,
b11010 I
#275000
0!
b0 ?
0<
b0 6
1#
1=
b100000 (
b100000 >
b101 *
b11100 ,
b11011 I
#285000
03
0.
1/
10
11
b11110 "
b11110 4
12
b1111111111111111 '
b1111111111111111 -
b1 +
b110 *
b11101 ,
b11100 I
0C
0G
#290000
0!
0%
1<
b11 6
1#
1=
17
08
19
1:
b111101 ?
1;
b1111111111111111 $
b1111111111111111 @
b11110 (
b11110 >
b1111111111111110 &
b1111111111111110 5
b0 *
#300000
b101 6
18
b111011 ?
09
b1111111111111111 $
b1111111111111111 @
b1111111111111101 &
b1111111111111101 5
b1 *
b11110 ,
b11101 I
b1111111111111111 A
b1111111111111111 E
#310000
b110 6
07
b111000 ?
08
b1111111111111111 $
b1111111111111111 @
b1111111111111011 &
b1111111111111011 5
b10 *
b11111 ,
b11110 I
#320000
b111 6
17
08
b111001 ?
09
b1111111111111111 $
b1111111111111111 @
b1111111111110111 &
b1111111111110111 5
b11 *
b100000 ,
b11111 I
#330000
0!
b1001 6
17
18
19
b110111 ?
0:
b1111111111111111 $
b1111111111111111 @
b1111111111101111 &
b1111111111101111 5
b100 *
b100001 ,
b100000 I
#340000
b1010 6
07
b110100 ?
08
b1111111111111111 $
b1111111111111111 @
b1111111111011111 &
b1111111111011111 5
b101 *
b100010 ,
b100001 I
#350000
b1011 6
17
08
b110101 ?
0:
b1111111111111111 $
b1111111111111111 @
b1111111110111111 &
b1111111110111111 5
b110 *
b100011 ,
b100010 I
#360000
07
09
b1100 6
18
b110010 ?
0:
b1111111111111111 $
b1111111111111111 @
b1111111101111111 &
b1111111101111111 5
b111 *
b100100 ,
b100011 I
#370000
0!
17
09
b1101 6
b110011 ?
0:
b1111111111111111 $
b1111111111111111 @
b1111111011111111 &
b1111111011111111 5
b1000 *
b100101 ,
b100100 I
#380000
07
08
09
b1110 6
b110000 ?
0:
b1111111111111111 $
b1111111111111111 @
b1111110111111111 &
b1111110111111111 5
b1001 *
b100110 ,
b100101 I
#390000
0!
17
08
09
b1111 6
b110001 ?
0:
b1111111111111111 $
b1111111111111111 @
b1111101111111111 &
b1111101111111111 5
b1010 *
b100111 ,
b100110 I
#400000
0!
0;
17
18
19
b10001 6
b101111 ?
1:
b1111111111111111 $
b1111111111111111 @
b1111011111111111 &
b1111011111111111 5
b1011 *
b101000 ,
b100111 I
#410000
b10010 6
07
b101100 ?
08
b1111111111111111 $
b1111111111111111 @
b1110111111111111 &
b1110111111111111 5
b1100 *
b101001 ,
b101000 I
#420000
0!
b10011 6
0;
17
b101101 ?
08
b1111111111111111 $
b1111111111111111 @
b1101111111111111 &
b1101111111111111 5
b1101 *
b101010 ,
b101001 I
#430000
b10100 6
07
09
0;
b101010 ?
18
b1111111111111111 $
b1111111111111111 @
b1011111111111111 &
b1011111111111111 5
b1110 *
b101011 ,
b101010 I
#440000
0!
b10101 6
17
09
b101011 ?
0;
b1111111111111111 $
b1111111111111111 @
b111111111111111 &
b111111111111111 5
b1111 *
b101100 ,
b101011 I
#450000
1!
0%
1#
1=
1<
b1 6
07
19
b111110 ?
1;
b1111111111111111 $
b1111111111111111 @
b11111 (
b11111 >
b1111111111111111 &
b1111111111111111 5
b0 *
b101101 ,
b101100 I
#460000
0%
1!
1#
1=
b111110 ?
1<
b10 6
b11100 (
b11100 >
b1 *
b101110 ,
b101101 I
1C
1G
#470000
0%
1!
1#
1=
b111110 ?
1<
b100 6
b11010 (
b11010 >
b10 *
b101111 ,
b101110 I
#480000
0%
1!
1#
1=
b111110 ?
1<
b1000 6
b10110 (
b10110 >
b11 *
b110000 ,
b101111 I
#490000
0%
1!
1#
1=
b111110 ?
1<
b10000 6
b1110 (
b1110 >
b100 *
b110001 ,
b110000 I
#500000
0!
b11110 ?
0<
b0 6
1#
1=
b111110 (
b111110 >
b101 *
b110010 ,
b110001 I
#510000
1.
13
1/
10
01
b100111 "
b100111 4
02
b1010010110100101 '
b1010010110100101 -
b10 +
b110 *
b110011 ,
b110010 I
0C
0G
#515000
0!
0%
1#
1=
07
08
19
0:
0;
b100 ?
0<
b11 6
b1010010110100101 $
b1010010110100101 @
b100111 (
b100111 >
b1010010110100100 &
b1010010110100100 5
b0 *
#525000
b101 6
18
b10 ?
09
b1010010110100101 $
b1010010110100101 @
b1010010110100111 &
b1010010110100111 5
b1 *
b110100 ,
b110011 I
b1010010110100101 A
b1010010110100101 E
#535000
b110 6
17
b1 ?
08
b1010010110100101 $
b1010010110100101 @
b1010010110100001 &
b1010010110100001 5
b10 *
b110101 ,
b110100 I
#545000
b111 6
07
08
b0 ?
09
b1010010110100101 $
b1010010110100101 @
b1010010110101101 &
b1010010110101101 5
b11 *
b110110 ,
b110101 I
#555000
0!
b1001 6
07
18
19
b1110 ?
1:
b1010010110100101 $
b1010010110100101 @
b1010010110110101 &
b1010010110110101 5
b100 *
b110111 ,
b110110 I
#565000
b1010 6
17
b1101 ?
08
b1010010110100101 $
b1010010110100101 @
b1010010110000101 &
b1010010110000101 5
b101 *
b111000 ,
b110111 I
#575000
b1011 6
07
08
b1100 ?
1:
b1010010110100101 $
b1010010110100101 @
b1010010111100101 &
b1010010111100101 5
b110 *
b111001 ,
b111000 I
#585000
17
09
b1100 6
18
b1011 ?
1:
b1010010110100101 $
b1010010110100101 @
b1010010100100101 &
b1010010100100101 5
b111 *
b111010 ,
b111001 I
#595000
0!
07
09
b1101 6
b1010 ?
1:
b1010010110100101 $
b1010010110100101 @
b1010010010100101 &
b1010010010100101 5
b1000 *
b111011 ,
b111010 I
#605000
17
08
09
b1110 6
b1001 ?
1:
b1010010110100101 $
b1010010110100101 @
b1010011110100101 &
b1010011110100101 5
b1001 *
b111100 ,
b111011 I
#615000
0!
07
08
09
b1111 6
b1000 ?
1:
b1010010110100101 $
b1010010110100101 @
b1010000110100101 &
b1010000110100101 5
b1010 *
b111101 ,
b111100 I
#625000
0!
1;
07
18
19
b10001 6
b10110 ?
0:
b1010010110100101 $
b1010010110100101 @
b1010110110100101 &
b1010110110100101 5
b1011 *
b111110 ,
b111101 I
#635000
b10010 6
17
b10101 ?
08
b1010010110100101 $
b1010010110100101 @
b1011010110100101 &
b1011010110100101 5
b1100 *
b111111 ,
b111110 I
#645000
0!
b10011 6
1;
07
b10100 ?
08
b1010010110100101 $
b1010010110100101 @
b1000010110100101 &
b1000010110100101 5
b1101 *
b1000000 ,
b111111 I
#655000
b10100 6
17
09
1;
b10011 ?
18
b1010010110100101 $
b1010010110100101 @
b1110010110100101 &
b1110010110100101 5
b1110 *
b1000001 ,
b1000000 I
#665000
0!
b10101 6
07
09
b10010 ?
1;
b1010010110100101 $
b1010010110100101 @
b10010110100101 &
b10010110100101 5
b1111 *
b1000010 ,
b1000001 I
#675000
1!
0%
1#
1=
0<
b1 6
17
19
b111 ?
0;
b1010010110100101 $
b1010010110100101 @
b100110 (
b100110 >
b1010010110100101 &
b1010010110100101 5
b0 *
b1000011 ,
b1000010 I
#685000
0%
1!
1#
1=
b111 ?
0<
b10 6
b100101 (
b100101 >
b1 *
b1000100 ,
b1000011 I
1C
1G
#695000
0%
1!
1#
1=
b111 ?
0<
b100 6
b100011 (
b100011 >
b10 *
b1000101 ,
b1000100 I
#705000
0%
1!
1#
1=
b111 ?
0<
b1000 6
b101111 (
b101111 >
b11 *
b1000110 ,
b1000101 I
#715000
0%
1!
1#
1=
b111 ?
0<
b10000 6
b110111 (
b110111 >
b100 *
b1000111 ,
b1000110 I
#725000
0!
b100111 ?
1<
b0 6
1#
1=
b111 (
b111 >
b101 *
b1001000 ,
b1000111 I
#735000
03
1.
0/
00
11
b11001 "
b11001 4
12
b1001000110100 '
b1001000110100 -
b11 +
b110 *
b1001001 ,
b1001000 I
0C
0G
#740000
0!
0%
1#
1=
1<
b11 6
07
18
09
1:
b111010 ?
1;
b1001000110100 $
b1001000110100 @
b11001 (
b11001 >
b1001000110101 &
b1001000110101 5
b0 *
