src/ParityStore.v
// =========================================================================
// Project ErrCo: ErrCo StarCore-1 Co-Proccessor Parity Store Module
// =========================================================================
//
// Project Group 10
//
// MEMBERS:
//   - Member 1 Zameer Mahomed, MHMZAM005
//   - Member 2 Mahir Khan, KHNMAH014

// File        : ParityStore.v
// Description : SEC-DED Hamming(22,16) 6-bit Parity Storage Module
// This module stores a data's parity in its own register that shadows the same address of the data stored in StarCore1
//Operates following StarCore1 GPR and Datamemory modules
// =============================================================================

`timescale 1ns / 1ps

module ParityStore (
    input clk,
    // --- Write port (synchronous) -------------------------------------------
    input        parity_write_en, // Write enable; write occurs on posedge clk
    input  [15:0] mem_access_addr,  // Source memory address

    input  [5:0] parity_in,       // Data to write from Encoder
    output [5:0] parity_out
);
    // -------------------------------------------------------------------------
    // 3-bit address for parity
    wire [2:0] parity_addr = mem_access_addr[2:0];
    //parity memory needs to contain 8 6-bit words. 
    reg [5:0] parity_store_ram [7:0];
     
    //zero out the register in first run
    initial begin
        for (integer i = 0; i < 8; i = i + 1) begin
            //blocking
            parity_store_ram[i] = 6'd0;
        end
    end

    //-------- Parity store ---------
    //on positiev clock edge
    always @(posedge clk) begin
        //only store the address if write is enabled
        if (parity_write_en) begin
            parity_store_ram[parity_addr] <= parity_in;
        end
    end
    //---------Parity Read---------
    assign parity_out = parity_store_ram[parity_addr];

endmodule

tb/ParityStore_tb.v
// =========================================================================
// Project ErrCo: ErrCo StarCore-1 Co-Proccessor Parity Store Module
// =========================================================================
//
// Project Group 10
//
// MEMBERS:
//   - Member 1 Zameer Mahomed, MHMZAM005
//   - Member 2 Mahir Khan, KHNMAH014
//
// File        : ParityStore_tb.v
// Description : Testbench for ParityStore.v - the 8 x 6-bit parity shadow memory.
//
//   Build & run (from tb/):
//     iverilog -Wall -I ../src -o ../build/ParityStore_sim ../src/ParityStore.v ParityStore_tb.v
//     cd ../test && ../build/ParityStore_sim
//     gtkwave ../waves/ParityStore_tb.vcd &
//
// What this verifies:
//   - all 8 slots initialise to 0
//   - write-then-read-back at the same address
//   - the read port is combinational (tracks address with no clock edge)
//   - writes to different addresses are independent (no aliasing)
//   - parity_write_en actually gates the write (en low -> no change)
//   - only the low 3 bits of mem_access_addr select the slot
//   - read-before-write ordering on a same-cycle write+read
// =============================================================================
`timescale 1ns / 1ps

module ParityStore_tb;

    // -------------------------------------------------------------------------
    // DUT signals
    // -------------------------------------------------------------------------
    reg         clk;
    reg         parity_write_en;
    reg  [15:0] mem_access_addr;
    reg  [5:0]  parity_in;
    wire [5:0]  parity_out;

    ParityStore uut (
        .clk             (clk),
        .parity_write_en (parity_write_en),
        .mem_access_addr (mem_access_addr),
        .parity_in       (parity_in),
        .parity_out      (parity_out)
    );

    // -------------------------------------------------------------------------
    // Clock: 10ns period
    // -------------------------------------------------------------------------
    initial clk = 1'b0;
    always #5 clk = ~clk;

    // -------------------------------------------------------------------------
    // Waveform dump
    // -------------------------------------------------------------------------
    initial begin
        $dumpfile("../waves/ParityStore_tb.vcd");
        $dumpvars(0, ParityStore_tb);
    end

    // -------------------------------------------------------------------------
    // Bookkeeping
    // -------------------------------------------------------------------------
    integer fail_count;
    integer test_id;
    integer i;

    initial begin
        fail_count = 0;
        test_id    = 1;
    end

    // -------------------------------------------------------------------------
    // Check task: compare parity_out against an expected value
    // -------------------------------------------------------------------------
    task check_parity;
        input [5:0]  got;
        input [5:0]  expected;
        input [63:0] id;
        begin
            if (got === expected) begin
                $display("PASS [T%0d]: parity_out = %b (0x%h), expected = %b (0x%h)",
                         id, got, got, expected, expected);
            end else begin
                $display("FAIL [T%0d]: parity_out = %b (0x%h), expected = %b (0x%h)",
                         id, got, got, expected, expected);
                fail_count = fail_count + 1;
            end
        end
    endtask

    // -------------------------------------------------------------------------
    // Helper: perform a synchronous write at a given address.
    // Sets up inputs, waits for the rising edge to land the write, then drops
    // the write-enable.  Leaves mem_access_addr pointing at the written slot.
    // -------------------------------------------------------------------------
    task do_write;
        input [15:0] addr;
        input [5:0]  data;
        begin
            @(negedge clk);                 // change inputs away from the edge
            mem_access_addr = addr;
            parity_in       = data;
            parity_write_en = 1'b1;
            @(posedge clk);                 // write commits here
            @(negedge clk);
            parity_write_en = 1'b0;
        end
    endtask

    // =========================================================================
    // Tests
    // =========================================================================
    initial begin
        // initialise
        parity_write_en = 1'b0;
        mem_access_addr = 16'd0;
        parity_in       = 6'd0;

        $display("=== ParityStore Testbench ===");

        // ---------------------------------------------------------------------
        // T1-T8 : every slot initialises to 0
        // ---------------------------------------------------------------------
        $display("");
        $display("--- T1-T8: all 8 slots initialise to 0 ---");
        #2; // let initial block settle, stay before first posedge activity
        for (i = 0; i < 8; i = i + 1) begin
            mem_access_addr = i[15:0];
            #1;
            check_parity(parity_out, 6'd0, test_id);
            test_id = test_id + 1;
        end

        // ---------------------------------------------------------------------
        // T9 : basic write-then-read-back at address 0
        // ---------------------------------------------------------------------
        $display("");
        $display("--- T9: write 0x2A to addr 0, read it back ---");
        do_write(16'd0, 6'h2A);
        mem_access_addr = 16'd0; #1;
        check_parity(parity_out, 6'h2A, test_id);
        test_id = test_id + 1;

        // ---------------------------------------------------------------------
        // T10 : combinational read - change address only, no clock edge,
        //       output must follow immediately
        // ---------------------------------------------------------------------
        $display("");
        $display("--- T10: read is combinational (addr change, no clk edge) ---");
        do_write(16'd5, 6'h15);             // put a known value in slot 5
        mem_access_addr = 16'd0;  #1;       // point at slot 0 (holds 0x2A from T9)
        mem_access_addr = 16'd5;  #1;       // switch to slot 5 with no edge between
        check_parity(parity_out, 6'h15, test_id);
        test_id = test_id + 1;

        // ---------------------------------------------------------------------
        // T11-T18 : address independence - write a distinct value to every
        //           slot, then read them all back. No aliasing.
        // ---------------------------------------------------------------------
        $display("");
        $display("--- T11-T18: 8 distinct values, one per slot, no aliasing ---");
        for (i = 0; i < 8; i = i + 1) begin
            // distinct 6-bit pattern per slot: 0x3F, 0x01, 0x02, ... pattern (i*9+7) masked
            do_write(i[15:0], (i*9 + 7) & 6'h3F);
        end
        for (i = 0; i < 8; i = i + 1) begin
            mem_access_addr = i[15:0]; #1;
            check_parity(parity_out, (i*9 + 7) & 6'h3F, test_id);
            test_id = test_id + 1;
        end

        // ---------------------------------------------------------------------
        // T19 : write-enable gating - with en LOW, a clock edge must NOT change
        //       the stored value
        // ---------------------------------------------------------------------
        $display("");
        $display("--- T19: parity_write_en LOW blocks the write ---");
        do_write(16'd3, 6'h3F);             // slot 3 := 0x3F
        @(negedge clk);
        mem_access_addr = 16'd3;
        parity_in       = 6'h00;            // try to overwrite with 0...
        parity_write_en = 1'b0;             // ...but enable is LOW
        @(posedge clk);                     // clock edge - should be ignored
        @(negedge clk);
        #1;
        check_parity(parity_out, 6'h3F, test_id);  // still 0x3F
        test_id = test_id + 1;

        // ---------------------------------------------------------------------
        // T20 : confirm the SAME slot then DOES update once enable is high
        // ---------------------------------------------------------------------
        $display("");
        $display("--- T20: same slot updates when enable is HIGH ---");
        do_write(16'd3, 6'h12);             // now actually overwrite slot 3
        mem_access_addr = 16'd3; #1;
        check_parity(parity_out, 6'h12, test_id);
        test_id = test_id + 1;

        // ---------------------------------------------------------------------
        // T21 : only the low 3 bits of mem_access_addr matter.
        //       addr 0x000B has low bits 011 = 3, so it must alias slot 3.
        // ---------------------------------------------------------------------
        $display("");
        $display("--- T21: high address bits ignored (0x000B -> slot 3) ---");
        mem_access_addr = 16'h000B; #1;     // 0b...1011 -> low 3 bits = 011 = 3
        check_parity(parity_out, 6'h12, test_id);  // same as slot 3 from T20
        test_id = test_id + 1;

        // ---------------------------------------------------------------------
        // T22 : write using a high-bit-laden address, read back with the
        //       plain 3-bit address - must land in the same slot.
        // ---------------------------------------------------------------------
        $display("");
        $display("--- T22: write at 0xFFFE, read at 0x0006 (both -> slot 6) ---");
        do_write(16'hFFFE, 6'h29);          // low 3 bits of 0xFFFE = 110 = 6
        mem_access_addr = 16'd6; #1;
        check_parity(parity_out, 6'h29, test_id);
        test_id = test_id + 1;

        // ---------------------------------------------------------------------
        // T23 : read-before-write ordering. In the same cycle that a write to
        //       slot 2 is committing, the read port should still show the OLD
        //       value until the edge passes, then the NEW value after.
        // ---------------------------------------------------------------------
        $display("");
        $display("--- T23: read-before-write on a same-cycle write to slot 2 ---");
        do_write(16'd2, 6'h0C);             // slot 2 := 0x0C (known starting value)
        @(negedge clk);
        mem_access_addr = 16'd2;
        parity_in       = 6'h33;
        parity_write_en = 1'b1;
        #1;
        // we are now between negedge and the next posedge: write has NOT committed
        check_parity(parity_out, 6'h0C, test_id);   // still old value
        test_id = test_id + 1;
        @(posedge clk);                      // write commits
        @(negedge clk);
        parity_write_en = 1'b0;
        #1;
        check_parity(parity_out, 6'h33, test_id);   // now new value
        test_id = test_id + 1;

        // ---------------------------------------------------------------------
        // Summary
        // ---------------------------------------------------------------------
        $display("");
        if (fail_count == 0)
            $display("=== ALL %0d TESTS PASSED ===", test_id - 1);
        else
            $display("=== %0d / %0d TESTS FAILED ===", fail_count, test_id - 1);

        $finish;
    end

endmodule

waves/ParityStore_tb.vcd
$date
	Thu May 14 23:41:26 2026
$end
$version
	Icarus Verilog
$end
$timescale
	1ps
$end
$scope module ParityStore_tb $end
$var wire 6 ! parity_out [5:0] $end
$var reg 1 " clk $end
$var reg 16 # mem_access_addr [15:0] $end
$var reg 6 $ parity_in [5:0] $end
$var reg 1 % parity_write_en $end
$var integer 32 & fail_count [31:0] $end
$var integer 32 ' i [31:0] $end
$var integer 32 ( test_id [31:0] $end
$scope module uut $end
$var wire 1 " clk $end
$var wire 16 ) mem_access_addr [15:0] $end
$var wire 6 * parity_in [5:0] $end
$var wire 6 + parity_out [5:0] $end
$var wire 1 % parity_write_en $end
$var wire 3 , parity_addr [2:0] $end
$scope begin $ivl_for_loop0 $end
$var integer 32 - i [31:0] $end
$upscope $end
$upscope $end
$scope task check_parity $end
$var reg 6 . expected [5:0] $end
$var reg 6 / got [5:0] $end
$var reg 64 0 id [63:0] $end
$upscope $end
$scope task do_write $end
$var reg 16 1 addr [15:0] $end
$var reg 6 2 data [5:0] $end
$upscope $end
$upscope $end
$enddefinitions $end
$comment Show the parameter values. $end
$dumpall
$end
#0
$dumpvars
bx 2
bx 1
bx 0
bx /
bx .
b1000 -
b0 ,
b0 +
b0 *
b0 )
b1 (
bx '
b0 &
0%
b0 $
b0 #
0"
b0 !
$end
#2000
b0 '
#3000
b1 ,
b1 #
b1 )
b1 '
b10 (
b1 0
b0 .
b0 /
#4000
b10 ,
b10 #
b10 )
b10 '
b11 (
b10 0
#5000
b11 ,
b11 #
b11 )
b11 '
b100 (
b11 0
1"
#6000
b100 ,
b100 #
b100 )
b100 '
b101 (
b100 0
#7000
b101 ,
b101 #
b101 )
b101 '
b110 (
b101 0
#8000
b110 ,
b110 #
b110 )
b110 '
b111 (
b110 0
#9000
b111 ,
b111 #
b111 )
b111 '
b1000 (
b111 0
#10000
b101010 2
b0 1
b1000 '
b1001 (
b1000 0
0"
#15000
1"
#20000
b0 ,
1%
b101010 $
b101010 *
b0 #
b0 )
0"
#25000
b101010 !
b101010 +
1"
#30000
0%
0"
#31000
b10101 2
b101 1
b1010 (
b1001 0
b101010 .
b101010 /
#35000
1"
#40000
b0 !
b0 +
b101 ,
1%
b10101 $
b10101 *
b101 #
b101 )
0"
#45000
b10101 !
b10101 +
1"
#50000
b101010 !
b101010 +
b0 ,
b0 #
b0 )
0%
0"
#51000
b10101 !
b10101 +
b101 ,
b101 #
b101 )
#52000
b111 2
b0 1
b0 '
b1011 (
b1010 0
b10101 .
b10101 /
#55000
1"
#60000
b101010 !
b101010 +
b0 ,
1%
b111 $
b111 *
b0 #
b0 )
0"
#65000
b111 !
b111 +
1"
#70000
b10000 2
b1 1
b1 '
0%
0"
#75000
1"
#80000
b0 !
b0 +
b1 ,
1%
b10000 $
b10000 *
b1 #
b1 )
0"
#85000
b10000 !
b10000 +
1"
#90000
b11001 2
b10 1
b10 '
0%
0"
#95000
1"
#100000
b0 !
b0 +
b10 ,
1%
b11001 $
b11001 *
b10 #
b10 )
0"
#105000
b11001 !
b11001 +
1"
#110000
b100010 2
b11 1
b11 '
0%
0"
#115000
1"
#120000
b0 !
b0 +
b11 ,
1%
b100010 $
b100010 *
b11 #
b11 )
0"
#125000
b100010 !
b100010 +
1"
#130000
b101011 2
b100 1
b100 '
0%
0"
#135000
1"
#140000
b0 !
b0 +
b100 ,
1%
b101011 $
b101011 *
b100 #
b100 )
0"
#145000
b101011 !
b101011 +
1"
#150000
b110100 2
b101 1
b101 '
0%
0"
#155000
1"
#160000
b10101 !
b10101 +
b101 ,
1%
b110100 $
b110100 *
b101 #
b101 )
0"
#165000
b110100 !
b110100 +
1"
#170000
b111101 2
b110 1
b110 '
0%
0"
#175000
1"
#180000
b0 !
b0 +
b110 ,
1%
b111101 $
b111101 *
b110 #
b110 )
0"
#185000
b111101 !
b111101 +
1"
#190000
b110 2
b111 1
b111 '
0%
0"
#195000
1"
#200000
b0 !
b0 +
b111 ,
1%
b110 $
b110 *
b111 #
b111 )
0"
#205000
b110 !
b110 +
1"
#210000
b111 !
b111 +
b0 ,
b0 #
b0 )
b0 '
0%
0"
#211000
b10000 !
b10000 +
b1 ,
b1 #
b1 )
b1 '
b1100 (
b1011 0
b111 .
b111 /
#212000
b11001 !
b11001 +
b10 ,
b10 #
b10 )
b10 '
b1101 (
b1100 0
b10000 .
b10000 /
#213000
b100010 !
b100010 +
b11 ,
b11 #
b11 )
b11 '
b1110 (
b1101 0
b11001 .
b11001 /
#214000
b101011 !
b101011 +
b100 ,
b100 #
b100 )
b100 '
b1111 (
b1110 0
b100010 .
b100010 /
#215000
b110100 !
b110100 +
b101 ,
b101 #
b101 )
b101 '
b10000 (
b1111 0
b101011 .
b101011 /
1"
#216000
b111101 !
b111101 +
b110 ,
b110 #
b110 )
b110 '
b10001 (
b10000 0
b110100 .
b110100 /
#217000
b110 !
b110 +
b111 ,
b111 #
b111 )
b111 '
b10010 (
b10001 0
b111101 .
b111101 /
#218000
b111111 2
b11 1
b1000 '
b10011 (
b10010 0
b110 .
b110 /
#220000
b100010 !
b100010 +
b11 ,
1%
b111111 $
b111111 *
b11 #
b11 )
0"
#225000
b111111 !
b111111 +
1"
#230000
0%
0"
#235000
1"
#240000
b0 $
b0 *
0"
#245000
1"
#250000
0"
#251000
b10010 2
b10100 (
b10011 0
b111111 .
b111111 /
#255000
1"
#260000
1%
b10010 $
b10010 *
0"
#265000
b10010 !
b10010 +
1"
#270000
0%
0"
#271000
b1011 #
b1011 )
b10101 (
b10100 0
b10010 .
b10010 /
#272000
b101001 2
b1111111111111110 1
b10110 (
b10101 0
#275000
1"
#280000
b111101 !
b111101 +
b110 ,
1%
b101001 $
b101001 *
b1111111111111110 #
b1111111111111110 )
0"
#285000
b101001 !
b101001 +
1"
#290000
b110 #
b110 )
0%
0"
#291000
b1100 2
b10 1
b10111 (
b10110 0
b101001 .
b101001 /
#295000
1"
#300000
b11001 !
b11001 +
b10 ,
1%
b1100 $
b1100 *
b10 #
b10 )
0"
#305000
b1100 !
b1100 +
1"
#310000
0%
0"
#315000
1"
#320000
1%
b110011 $
b110011 *
0"
#321000
b11000 (
b10111 0
b1100 .
b1100 /
#325000
b110011 !
b110011 +
1"
#330000
0%
0"
#331000
b11001 (
b11000 0
b110011 .
b110011 /
